{
  "1": "\uCC3D\uC138\uAE30",
  "2": "\uCD9C\uC560\uAD7D\uAE30",
  "3": "\uB808\uC704\uAE30",
  "4": "\uBBFC\uC218\uAE30",
  "5": "\uC2E0\uBA85\uAE30",
  "6": "\uC5EC\uD638\uC218\uC544",
  "7": "\uC0AC\uC0AC\uAE30",
  "8": "\uB8FB\uAE30",
  "9": "\uC0AC\uBB34\uC5D8\uC0C1",
  "10": "\uC0AC\uBB34\uC5D8\uD558",
  "11": "\uC5F4\uC655\uAE30\uC0C1",
  "12": "\uC5F4\uC655\uAE30\uD558",
  "13": "\uC5ED\uB300\uC0C1",
  "14": "\uC5ED\uB300\uD558",
  "15": "\uC5D0\uC2A4\uB77C",
  "16": "\uB290\uD5E4\uBBF8\uC57C",
  "17": "\uC5D0\uC2A4\uB354",
  "18": "\uC6A5\uAE30",
  "19": "\uC2DC\uD3B8",
  "20": "\uC7A0\uC5B8",
  "21": "\uC804\uB3C4\uC11C",
  "22": "\uC544\uAC00",
  "23": "\uC774\uC0AC\uC57C",
  "24": "\uC608\uB808\uBBF8\uC57C",
  "25": "\uC608\uB808\uBBF8\uC57C \uC560\uAC00",
  "26": "\uC5D0\uC2A4\uAC94",
  "27": "\uB2E4\uB2C8\uC5D8",
  "28": "\uD638\uC138\uC544",
  "29": "\uC694\uC5D8",
  "30": "\uC544\uBAA8\uC2A4",
  "31": "\uC624\uBC14\uB31C",
  "32": "\uC694\uB098",
  "33": "\uBBF8\uAC00",
  "34": "\uB098\uD6D4",
  "35": "\uD558\uBC15\uAD6D",
  "36": "\uC2A4\uBC14\uB0D0",
  "37": "\uD559\uAC1C",
  "38": "\uC2A4\uAC00\uB7B4",
  "39": "\uB9D0\uB77C\uAE30",
  "40": "\uB9C8\uD0DC\uBCF5\uC74C",
  "41": "\uB9C8\uAC00\uBCF5\uC74C",
  "42": "\uB204\uAC00\uBCF5\uC74C",
  "43": "\uC694\uD55C\uBCF5\uC74C",
  "44": "\uC0AC\uB3C4\uD589\uC804",
  "45": "\uB85C\uB9C8\uC11C",
  "46": "\uACE0\uB9B0\uB3C4\uC804\uC11C",
  "47": "\uACE0\uB9B0\uB3C4\uD6C4\uC11C",
  "48": "\uAC08\uB77C\uB514\uC544\uC11C",
  "49": "\uC5D0\uBCA0\uC18C\uC11C",
  "50": "\uBE4C\uB9BD\uBCF4\uC11C",
  "51": "\uACE8\uB85C\uC0C8\uC11C",
  "52": "\uB370\uC0B4\uB85C\uB2C8\uAC00\uC804\uC11C",
  "53": "\uB370\uC0B4\uB85C\uB2C8\uAC00\uD6C4\uC11C",
  "54": "\uB514\uBAA8\uB370\uC804\uC11C",
  "55": "\uB514\uBAA8\uB370\uD6C4\uC11C",
  "56": "\uB514\uB3C4\uC11C",
  "57": "\uBE4C\uB808\uBAAC\uC11C",
  "58": "\uD788\uBE0C\uB9AC\uC11C",
  "59": "\uC57C\uACE0\uBCF4\uC11C",
  "60": "\uBCA0\uB4DC\uB85C\uC804\uC11C",
  "61": "\uBCA0\uB4DC\uB85C\uD6C4\uC11C",
  "62": "\uC694\uD55C\uC77C\uC11C",
  "63": "\uC694\uD55C\uC774\uC11C",
  "64": "\uC694\uD55C\uC0BC\uC11C",
  "65": "\uC720\uB2E4\uC11C",
  "66": "\uC694\uD55C\uACC4\uC2DC\uB85D"
}